{
  "$schema": "https://wails.io/schemas/config.v2.json",
  "name": "VM Cat",
  "outputfilename": "VM Cat",
  "frontend:install": "npm install",
  "frontend:build": "npm run build",
  "frontend:dev:watcher": "npm run dev",
  "frontend:dev:serverUrl": "auto",
  "author": {
    "name": "Blake Li",
    "email": "BlakeLiAFK@gmail.com"
  },
  "info": {
    "companyName": "Blake Li",
    "productName": "VM Cat",
    "productVersion": "0.2.0",
    "copyright": "Copyright 2026 Blake Li. All rights reserved.",
    "comments": "Lightweight VM management tool via SSH"
  }
}
